[
    {
        "mot": "risque"
    },
    {
        "mot": "actuel"
    },
    {
        "mot": "cheval"
    },
    {
        "mot": "paquet"
    },
    {
        "mot": "examen"
    },
    {
        "mot": "buveur"
    },
    {
        "mot": "cabine"
    },
    {
        "mot": "orange"
    },
    {
        "mot": "soleil"
    },
    {
        "mot": "fleurs"
    },
    {
        "mot": "nuages"
    },
    {
        "mot": "rivage"
    },
    {
        "mot": "forger"
    },
    {
        "mot": "jardin"
    },
    {
        "mot": "livres"
    },
    {
        "mot": "pluies"
    },
    {
        "mot": "bouche"
    },
    {
        "mot": "chante"
    },
    {
        "mot": "esprit"
    },
    {
        "mot": "valeur"
    },
    {
        "mot": "brises"
    },
    {
        "mot": "douces"
    },
    {
        "mot": "graine"
    },
    {
        "mot": "humeur"
    },
    {
        "mot": "joyeux"
    }
]